[
  {
    "Author": "rumia-moe",
    "Name": "PatMeMoodles",
    "InternalName": "PatMeMoodles",
    "AssemblyVersion": "1.0.0.1",
    "Description": "Display emote counters with the Moodles plugin.",
    "ApplicableVersion": "any",
    "RepoUrl": "https://github.com/rumia-moe/PatMeMoodles",
    "Tags": [
      "emote",
      "plugin",
      "moodles"
    ],
    "DalamudApiLevel": "14",
    "TestingDalamudApiLevel": "14",
    "LoadPriority": 0,
    "Punchline": "Emotes counters with icons!",
    "IsHide": "False",
    "IsTestingExclusive": "False",
    "DownloadLinkInstall": "https://github.com/rumia-moe/PatMeMoodles/releases/download/1.0.0.1/Release.zip",
    "DownloadLinkUpdate": "https://github.com/rumia-moe/PatMeMoodles/releases/download/1.0.0.1/Release.zip"
  }
]
